pyx/__init__.py
pyx/cli.py
pyx/contrib/__init__.py
pyx/contrib/auth.py
pyx/core/ai.py
pyx/core/cache.py
pyx/core/context.py
pyx/core/database.py
pyx/core/docs.py
pyx/core/edge.py
pyx/core/env.py
pyx/core/events.py
pyx/core/logging.py
pyx/core/middleware.py
pyx/core/plugins.py
pyx/core/reactive.py
pyx/core/router.py
pyx/core/security.py
pyx/core/server.py
pyx/core/session.py
pyx/core/ssg.py
pyx/core/state.py
pyx/core/storage.py
pyx/core/tasks.py
pyx/core/testing.py
pyx/core/websocket.py
pyx/data/database.py
pyx/lib/audit.py
pyx/lib/auth.py
pyx/lib/email.py
pyx/lib/i18n.py
pyx/lib/jobs.py
pyx/lib/pwa.py
pyx/lib/seo.py
pyx/lib/validation.py
pyx/lib/admin/__init__.py
pyx/lib/admin/views.py
pyx/web/a11y.py
pyx/web/animation.py
pyx/web/assets.py
pyx/web/client.py
pyx/web/colors.py
pyx/web/devtools.py
pyx/web/layout.py
pyx/web/responsive.py
pyx/web/styles.py
pyx/web/suspense.py
pyx/web/theme.py
pyx/web/ui.py
pyx/web/validation.py
pyx/web/components/__init__.py
pyx/web/components/advanced.py
pyx/web/components/chart.py
pyx/web/components/components.py
pyx/web/components/dashboard.py
pyx/web/components/datagrid.py
pyx/web/components/dragdrop.py
pyx/web/components/essential.py
pyx/web/components/forms.py
pyx/web/components/lucide.py
pyx/web/components/toast.py
pyx/web/components/trading.py
pyx/web/components/upload.py
usepyx-0.1.2.dist-info/licenses/LICENSE
usepyx-0.1.2.dist-info/METADATA
usepyx-0.1.2.dist-info/WHEEL
usepyx-0.1.2.dist-info/entry_points.txt
usepyx-0.1.2.dist-info/top_level.txt
usepyx-0.1.2.dist-info/RECORD
