Metadata-Version: 2.4
Name: usepyx
Version: 0.1.2
Summary: Pure Python Full-Stack Framework: No JavaScript, no HTML mess, just Zen Mode.
Author-email: PyX Team <dev@pyx.com>
License: MIT License
Project-URL: Homepage, https://github.com/sukirman1901/usePyX
Project-URL: Documentation, https://github.com/sukirman1901/usePyX/blob/main/README.md
Project-URL: Repository, https://github.com/sukirman1901/usePyX.git
Project-URL: Issues, https://github.com/sukirman1901/usePyX/issues
Keywords: web,framework,python,frontend,fullstack,pyx
Classifier: Development Status :: 4 - Beta
Classifier: Environment :: Web Environment
Classifier: Intended Audience :: Developers
Classifier: License :: OSI Approved :: MIT License
Classifier: Operating System :: OS Independent
Classifier: Programming Language :: Python :: 3
Classifier: Programming Language :: Python :: 3.9
Classifier: Programming Language :: Python :: 3.10
Classifier: Programming Language :: Python :: 3.11
Classifier: Programming Language :: Python :: 3.12
Classifier: Topic :: Internet :: WWW/HTTP :: Dynamic Content
Classifier: Topic :: Software Development :: Libraries :: Application Frameworks
Requires-Python: >=3.9
License-File: LICENSE
Requires-Dist: fastapi
Requires-Dist: uvicorn
Requires-Dist: websockets
Requires-Dist: granian
Requires-Dist: sqlmodel
Requires-Dist: typer
Requires-Dist: passlib[bcrypt]
Requires-Dist: python-jose[cryptography]
Requires-Dist: jinja2
Requires-Dist: openai
Requires-Dist: anthropic
Requires-Dist: google-generativeai
Requires-Dist: boto3
Dynamic: license-file
